[
  {
    "filename": "96784e9b540f9360.jpg",
    "original_url": "https://upload.wikimedia.org/wikipedia/commons/b/b2/White_Desert_Egypt_1.jpg",
    "title": "File:White Desert Egypt 1.jpg",
    "license": "CC BY-SA 4.0",
    "artist": "<a href=\"//commons.wikimedia.org/wiki/User:Myousry6666\" title=\"User:Myousry6666\">Myousry6666</a>",
    "width": 5315,
    "height": 3543,
    "source": "wikimedia_commons",
    "downloaded_at": "2026-03-02T22:47:31"
  },
  {
    "filename": "2beaa427eed22335.jpg",
    "original_url": "https://upload.wikimedia.org/wikipedia/commons/a/aa/White_Desert_Egypt.jpg",
    "title": "File:White Desert Egypt.jpg",
    "license": "CC BY-SA 4.0",
    "artist": "<a href=\"//commons.wikimedia.org/wiki/User:Myousry6666\" title=\"User:Myousry6666\">Myousry6666</a>",
    "width": 5315,
    "height": 3543,
    "source": "wikimedia_commons",
    "downloaded_at": "2026-03-02T22:47:31"
  },
  {
    "filename": "503fd7492f002f5c.jpg",
    "original_url": "https://upload.wikimedia.org/wikipedia/commons/2/2c/White_Desert_Egypt_2.jpg",
    "title": "File:White Desert Egypt 2.jpg",
    "license": "CC BY-SA 4.0",
    "artist": "<a href=\"//commons.wikimedia.org/wiki/User:Myousry6666\" title=\"User:Myousry6666\">Myousry6666</a>",
    "width": 5315,
    "height": 3543,
    "source": "wikimedia_commons",
    "downloaded_at": "2026-03-02T22:47:31"
  },
  {
    "filename": "5e5b4b717cddf2a9.jpg",
    "original_url": "https://upload.wikimedia.org/wikipedia/commons/3/38/White_Desert_egypt_3.jpg",
    "title": "File:White Desert egypt 3.jpg",
    "license": "CC BY-SA 4.0",
    "artist": "<a href=\"//commons.wikimedia.org/wiki/User:Myousry6666\" title=\"User:Myousry6666\">Myousry6666</a>",
    "width": 4000,
    "height": 6000,
    "source": "wikimedia_commons",
    "downloaded_at": "2026-03-02T22:47:31"
  },
  {
    "filename": "2badfdbaca6f330f.jpg",
    "original_url": "https://upload.wikimedia.org/wikipedia/commons/6/60/White_Desert_Egypt_4.jpg",
    "title": "File:White Desert Egypt 4.jpg",
    "license": "CC BY-SA 4.0",
    "artist": "<a href=\"//commons.wikimedia.org/wiki/User:Myousry6666\" title=\"User:Myousry6666\">Myousry6666</a>",
    "width": 3543,
    "height": 5315,
    "source": "wikimedia_commons",
    "downloaded_at": "2026-03-02T22:47:31"
  },
  {
    "filename": "0262ae0fd8801a1b.jpg",
    "original_url": "https://upload.wikimedia.org/wikipedia/commons/8/81/White_Desert_Egypt_5.jpg",
    "title": "File:White Desert Egypt 5.jpg",
    "license": "CC BY-SA 4.0",
    "artist": "<a href=\"//commons.wikimedia.org/wiki/User:Myousry6666\" title=\"User:Myousry6666\">Myousry6666</a>",
    "width": 5315,
    "height": 3543,
    "source": "wikimedia_commons",
    "downloaded_at": "2026-03-02T22:47:31"
  },
  {
    "filename": "50afee5791ada61c.jpg",
    "original_url": "https://upload.wikimedia.org/wikipedia/commons/9/92/%D8%A7%D9%84%D8%B5%D8%AD%D8%B1%D8%A7%D8%A1_%D8%A7%D9%84%D8%A8%D9%8A%D8%B6%D8%A7%D8%A1.jpg",
    "title": "File:الصحراء البيضاء.jpg",
    "license": "CC BY-SA 4.0",
    "artist": "<a href=\"//commons.wikimedia.org/w/index.php?title=User:Ahmed_abd_elkader_mohamed&amp;action=edit&amp;redlink=1\" class=\"new\" title=\"User:Ahmed abd elkader mohamed (page does not exist)\">Ahmed abd elkader mohamed</a>",
    "width": 3384,
    "height": 5076,
    "source": "wikimedia_commons",
    "downloaded_at": "2026-03-02T22:47:31"
  },
  {
    "filename": "5f28ff27d7f23b72.jpg",
    "original_url": "https://upload.wikimedia.org/wikipedia/commons/1/15/%D8%A7%D9%84%D8%B5%D8%AD%D8%B1%D8%A7%D8%A1_%D8%A7%D9%84%D8%A8%D9%8A%D8%B6%D8%A7%D8%A1_-_%D9%85%D8%B3%D8%A7%D8%B1_%D8%A7%D9%84%D9%86%D8%AC%D9%88%D9%85.jpg",
    "title": "File:الصحراء البيضاء - مسار النجوم.jpg",
    "license": "CC BY-SA 4.0",
    "artist": "<a href=\"//commons.wikimedia.org/w/index.php?title=User:Ahmed_abd_elkader_mohamed&amp;action=edit&amp;redlink=1\" class=\"new\" title=\"User:Ahmed abd elkader mohamed (page does not exist)\">Ahmed abd elkader mohamed</a>",
    "width": 5097,
    "height": 3157,
    "source": "wikimedia_commons",
    "downloaded_at": "2026-03-02T22:47:31"
  },
  {
    "filename": "9253c8d6d5a32589.jpg",
    "original_url": "https://upload.wikimedia.org/wikipedia/commons/d/d1/%D9%85%D8%B3%D8%A7%D8%B1_%D8%A7%D9%84%D9%86%D8%AC%D9%88%D9%85_-_%D8%A7%D9%84%D8%B5%D8%AD%D8%B1%D8%A7%D8%A1_%D8%A7%D9%84%D8%A8%D9%8A%D8%B6%D8%A7%D8%A1.jpg",
    "title": "File:مسار النجوم - الصحراء البيضاء.jpg",
    "license": "CC BY-SA 4.0",
    "artist": "<a href=\"//commons.wikimedia.org/w/index.php?title=User:Ahmed_abd_elkader_mohamed&amp;action=edit&amp;redlink=1\" class=\"new\" title=\"User:Ahmed abd elkader mohamed (page does not exist)\">Ahmed abd elkader mohamed</a>",
    "width": 4962,
    "height": 3129,
    "source": "wikimedia_commons",
    "downloaded_at": "2026-03-02T22:47:31"
  },
  {
    "filename": "86a1b733d13e96b8.jpg",
    "original_url": "https://upload.wikimedia.org/wikipedia/commons/a/ac/%D8%A7%D9%84%D8%B5%D8%AD%D8%B1%D8%A7%D8%A1_%D8%A7%D9%84%D8%A8%D9%8A%D8%B6%D8%A7%D8%A1_%D8%A8%D9%85%D8%B5%D8%B1.jpg",
    "title": "File:الصحراء البيضاء بمصر.jpg",
    "license": "CC BY-SA 4.0",
    "artist": "<a href=\"//commons.wikimedia.org/w/index.php?title=User:Ahmed_Mandour&amp;action=edit&amp;redlink=1\" class=\"new\" title=\"User:Ahmed Mandour (page does not exist)\">Ahmed Mandour</a>",
    "width": 768,
    "height": 697,
    "source": "wikimedia_commons",
    "downloaded_at": "2026-03-02T22:47:31"
  },
  {
    "filename": "ea2c455c14bc4553.jpg",
    "original_url": "https://upload.wikimedia.org/wikipedia/commons/a/aa/%D8%AC%D9%85%D8%A7%D9%84_%D8%A7%D9%84%D8%B5%D8%AD%D8%B1%D8%A7%D8%A1_%D8%A7%D9%84%D8%A8%D9%8A%D8%B6%D8%A7%D8%A1.jpg",
    "title": "File:جمال الصحراء البيضاء.jpg",
    "license": "CC BY-SA 4.0",
    "artist": "<a href=\"//commons.wikimedia.org/wiki/User:Cherif_hegazy\" title=\"User:Cherif hegazy\">Cherif hegazy</a>",
    "width": 3264,
    "height": 2448,
    "source": "wikimedia_commons",
    "downloaded_at": "2026-03-02T22:47:31"
  },
  {
    "filename": "501dd370ec9f528f.jpg",
    "original_url": "https://upload.wikimedia.org/wikipedia/commons/a/a9/White_Desert_National_Park_banner.jpg",
    "title": "File:White Desert National Park banner.jpg",
    "license": "CC BY 3.0",
    "artist": "<a rel=\"nofollow\" class=\"external text\" href=\"https://web.archive.org/web/20161027211547/http://www.panoramio.com/user/7771407?with_photo_id=100915201\">L-BBE</a>",
    "width": 5612,
    "height": 802,
    "source": "wikimedia_commons",
    "downloaded_at": "2026-03-03T00:49:22"
  },
  {
    "filename": "fc836dd0a5f93854.jpg",
    "original_url": "https://upload.wikimedia.org/wikipedia/commons/f/f7/A_lost_horse_in_the_White_Desert_National_Park.jpg",
    "title": "File:A lost horse in the White Desert National Park.jpg",
    "license": "CC BY-SA 4.0",
    "artist": "<a href=\"//commons.wikimedia.org/w/index.php?title=User:AmiraAdel93&amp;action=edit&amp;redlink=1\" class=\"new\" title=\"User:AmiraAdel93 (page does not exist)\">AmiraAdel93</a>",
    "width": 5029,
    "height": 3353,
    "source": "wikimedia_commons",
    "downloaded_at": "2026-03-03T00:49:22"
  },
  {
    "filename": "0359542b4cb6a8dd.jpg",
    "original_url": "https://upload.wikimedia.org/wikipedia/commons/b/be/White_Desert_National_Park.jpg",
    "title": "File:White Desert National Park.jpg",
    "license": "CC BY-SA 4.0",
    "artist": "<a href=\"//commons.wikimedia.org/w/index.php?title=User:AmiraAdel93&amp;action=edit&amp;redlink=1\" class=\"new\" title=\"User:AmiraAdel93 (page does not exist)\">AmiraAdel93</a>",
    "width": 5184,
    "height": 3456,
    "source": "wikimedia_commons",
    "downloaded_at": "2026-03-03T00:49:22"
  },
  {
    "filename": "5f2c5014d59eecab.jpg",
    "original_url": "https://upload.wikimedia.org/wikipedia/commons/8/8a/Saharan_White_Desert%2C_Farafra%2C_D1.jpg",
    "title": "File:Saharan White Desert, Farafra, D1.jpg",
    "license": "CC BY 2.5",
    "artist": "<a href=\"https://en.wikipedia.org/wiki/User:Zadokite\" class=\"extiw\" title=\"wikipedia:User:Zadokite\">Zadokite</a> at <a href=\"https://en.wikipedia.org/wiki/\" class=\"extiw\" title=\"wikipedia:\">English Wikipedia</a>",
    "width": 800,
    "height": 1200,
    "source": "wikimedia_categories",
    "downloaded_at": "2026-03-03T01:05:54"
  },
  {
    "filename": "f2f57d7b474b12de.jpg",
    "original_url": "https://upload.wikimedia.org/wikipedia/commons/3/33/Al_Farafrah%2C_New_Valley_Governorate%2C_Egypt_-_panoramio_%282%29.jpg",
    "title": "File:Al Farafrah, New Valley Governorate, Egypt - panoramio (2).jpg",
    "license": "CC BY 3.0",
    "artist": "<a rel=\"nofollow\" class=\"external text\" href=\"https://web.archive.org/web/20161027173652/http://www.panoramio.com/user/7771407?with_photo_id=100915145\">L-BBE</a>",
    "width": 3744,
    "height": 5616,
    "source": "wikimedia_categories",
    "downloaded_at": "2026-03-03T01:05:54"
  },
  {
    "filename": "82bbd858dea8053e.jpg",
    "original_url": "https://upload.wikimedia.org/wikipedia/commons/6/6a/Al_Farafrah%2C_New_Valley_Governorate%2C_Egypt_-_panoramio_%2811%29.jpg",
    "title": "File:Al Farafrah, New Valley Governorate, Egypt - panoramio (11).jpg",
    "license": "CC BY 3.0",
    "artist": "<a rel=\"nofollow\" class=\"external text\" href=\"https://web.archive.org/web/20161027211547/http://www.panoramio.com/user/7771407?with_photo_id=100915201\">L-BBE</a>",
    "width": 5616,
    "height": 3744,
    "source": "wikimedia_categories",
    "downloaded_at": "2026-03-03T01:05:54"
  },
  {
    "filename": "7311ff3e1c8ccc90.jpg",
    "original_url": "https://upload.wikimedia.org/wikipedia/commons/6/6b/Al_Farafrah%2C_New_Valley_Governorate%2C_Egypt_-_panoramio_%2812%29.jpg",
    "title": "File:Al Farafrah, New Valley Governorate, Egypt - panoramio (12).jpg",
    "license": "CC BY 3.0",
    "artist": "<a rel=\"nofollow\" class=\"external text\" href=\"https://web.archive.org/web/20161029151021/http://www.panoramio.com/user/7771407?with_photo_id=100915195\">L-BBE</a>",
    "width": 3744,
    "height": 5616,
    "source": "wikimedia_categories",
    "downloaded_at": "2026-03-03T01:05:54"
  },
  {
    "filename": "a05ce1af6b11e093.jpg",
    "original_url": "https://upload.wikimedia.org/wikipedia/commons/0/0f/Al_Farafrah%2C_New_Valley_Governorate%2C_Egypt_-_panoramio_%2813%29.jpg",
    "title": "File:Al Farafrah, New Valley Governorate, Egypt - panoramio (13).jpg",
    "license": "CC BY 3.0",
    "artist": "<a rel=\"nofollow\" class=\"external text\" href=\"https://web.archive.org/web/20161027211604/http://www.panoramio.com/user/7771407?with_photo_id=100915206\">L-BBE</a>",
    "width": 3674,
    "height": 5511,
    "source": "wikimedia_categories",
    "downloaded_at": "2026-03-03T01:05:54"
  },
  {
    "filename": "4700e49e99dc53d8.jpg",
    "original_url": "https://upload.wikimedia.org/wikipedia/commons/a/a7/Al_Farafrah%2C_New_Valley_Governorate%2C_Egypt_-_panoramio_%2814%29.jpg",
    "title": "File:Al Farafrah, New Valley Governorate, Egypt - panoramio (14).jpg",
    "license": "CC BY 3.0",
    "artist": "<a rel=\"nofollow\" class=\"external text\" href=\"https://web.archive.org/web/20161029165313/http://www.panoramio.com/user/7771407?with_photo_id=100915212\">L-BBE</a>",
    "width": 5551,
    "height": 3701,
    "source": "wikimedia_categories",
    "downloaded_at": "2026-03-03T01:05:54"
  },
  {
    "filename": "8bf0997bc568433d.jpg",
    "original_url": "https://upload.wikimedia.org/wikipedia/commons/d/d8/Al_Farafrah%2C_New_Valley_Governorate%2C_Egypt_-_panoramio_%2815%29.jpg",
    "title": "File:Al Farafrah, New Valley Governorate, Egypt - panoramio (15).jpg",
    "license": "CC BY 3.0",
    "artist": "<a rel=\"nofollow\" class=\"external text\" href=\"https://web.archive.org/web/20161029165336/http://www.panoramio.com/user/7771407?with_photo_id=100915217\">L-BBE</a>",
    "width": 5616,
    "height": 3744,
    "source": "wikimedia_categories",
    "downloaded_at": "2026-03-03T01:05:54"
  },
  {
    "filename": "ae39d66541fce550.jpg",
    "original_url": "https://upload.wikimedia.org/wikipedia/commons/1/12/Al_Farafrah%2C_New_Valley_Governorate%2C_Egypt_-_panoramio_%2816%29.jpg",
    "title": "File:Al Farafrah, New Valley Governorate, Egypt - panoramio (16).jpg",
    "license": "CC BY 3.0",
    "artist": "<a rel=\"nofollow\" class=\"external text\" href=\"https://web.archive.org/web/20161028151423/http://www.panoramio.com/user/7771407?with_photo_id=100915222\">L-BBE</a>",
    "width": 3521,
    "height": 5281,
    "source": "wikimedia_categories",
    "downloaded_at": "2026-03-03T01:05:54"
  },
  {
    "filename": "9a68e980ffb5d266.jpg",
    "original_url": "https://upload.wikimedia.org/wikipedia/commons/0/03/Al_Farafrah%2C_New_Valley_Governorate%2C_Egypt_-_panoramio_%2817%29.jpg",
    "title": "File:Al Farafrah, New Valley Governorate, Egypt - panoramio (17).jpg",
    "license": "CC BY 3.0",
    "artist": "<a rel=\"nofollow\" class=\"external text\" href=\"https://web.archive.org/web/20161027211618/http://www.panoramio.com/user/7771407?with_photo_id=100915209\">L-BBE</a>",
    "width": 3744,
    "height": 5616,
    "source": "wikimedia_categories",
    "downloaded_at": "2026-03-03T01:05:54"
  },
  {
    "filename": "50817585773b4a41.jpg",
    "original_url": "https://upload.wikimedia.org/wikipedia/commons/5/53/Al_Farafrah%2C_New_Valley_Governorate%2C_Egypt_-_panoramio_%2818%29.jpg",
    "title": "File:Al Farafrah, New Valley Governorate, Egypt - panoramio (18).jpg",
    "license": "CC BY 3.0",
    "artist": "<a rel=\"nofollow\" class=\"external text\" href=\"https://web.archive.org/web/20161029165333/http://www.panoramio.com/user/7771407?with_photo_id=100915215\">L-BBE</a>",
    "width": 3589,
    "height": 5384,
    "source": "wikimedia_categories",
    "downloaded_at": "2026-03-03T01:05:54"
  },
  {
    "filename": "abb7370c84e809a9.jpg",
    "original_url": "https://upload.wikimedia.org/wikipedia/commons/d/de/Al_Farafrah%2C_New_Valley_Governorate%2C_Egypt_-_panoramio_%2819%29.jpg",
    "title": "File:Al Farafrah, New Valley Governorate, Egypt - panoramio (19).jpg",
    "license": "CC BY 3.0",
    "artist": "<a rel=\"nofollow\" class=\"external text\" href=\"https://web.archive.org/web/20161029034320/http://www.panoramio.com/user/7771407?with_photo_id=100915233\">L-BBE</a>",
    "width": 3569,
    "height": 5353,
    "source": "wikimedia_categories",
    "downloaded_at": "2026-03-03T01:05:54"
  },
  {
    "filename": "ee701f3f60b561d4.jpg",
    "original_url": "https://upload.wikimedia.org/wikipedia/commons/5/5c/Al_Farafrah%2C_New_Valley_Governorate%2C_Egypt_-_panoramio_%2820%29.jpg",
    "title": "File:Al Farafrah, New Valley Governorate, Egypt - panoramio (20).jpg",
    "license": "CC BY 3.0",
    "artist": "<a rel=\"nofollow\" class=\"external text\" href=\"https://web.archive.org/web/20161029165324/http://www.panoramio.com/user/7771407?with_photo_id=100915213\">L-BBE</a>",
    "width": 5506,
    "height": 3671,
    "source": "wikimedia_categories",
    "downloaded_at": "2026-03-03T01:05:54"
  },
  {
    "filename": "3cc33709fa83c9dd.jpg",
    "original_url": "https://upload.wikimedia.org/wikipedia/commons/4/4a/Al_Farafrah%2C_New_Valley_Governorate%2C_Egypt_-_panoramio_%2821%29.jpg",
    "title": "File:Al Farafrah, New Valley Governorate, Egypt - panoramio (21).jpg",
    "license": "CC BY 3.0",
    "artist": "<a rel=\"nofollow\" class=\"external text\" href=\"https://web.archive.org/web/20161028151431/http://www.panoramio.com/user/7771407?with_photo_id=100915227\">L-BBE</a>",
    "width": 5352,
    "height": 3568,
    "source": "wikimedia_categories",
    "downloaded_at": "2026-03-03T01:05:54"
  },
  {
    "filename": "8dcd810c16d104fa.jpg",
    "original_url": "https://upload.wikimedia.org/wikipedia/commons/e/e2/Al_Farafrah%2C_New_Valley_Governorate%2C_Egypt_-_panoramio_%2827%29.jpg",
    "title": "File:Al Farafrah, New Valley Governorate, Egypt - panoramio (27).jpg",
    "license": "CC BY-SA 3.0",
    "artist": "<a rel=\"nofollow\" class=\"external text\" href=\"https://web.archive.org/web/20161029065116/http://www.panoramio.com/user/8081383?with_photo_id=101066378\">Jakub Perka</a>",
    "width": 2592,
    "height": 1944,
    "source": "wikimedia_categories",
    "downloaded_at": "2026-03-03T01:05:54"
  },
  {
    "filename": "ae1b488f2f00ecd9.jpg",
    "original_url": "https://upload.wikimedia.org/wikipedia/commons/a/af/%22White_Desert_morning%22_by_CairoCarol_is_licensed_under_CC_BY_2.0.jpg",
    "title": "File:\"White Desert morning\" by CairoCarol is licensed under CC BY 2.0.jpg",
    "license": "CC BY 2.0",
    "artist": "<a rel=\"nofollow\" class=\"external text\" href=\"https://www.flickr.com/people/78365458@N00\">Carol Walker</a> from Jakarta, Indonesia",
    "width": 2560,
    "height": 1920,
    "source": "wikimedia_categories",
    "downloaded_at": "2026-03-03T01:05:54"
  },
  {
    "filename": "e3791f668bb87f92.jpg",
    "original_url": "https://upload.wikimedia.org/wikipedia/commons/2/23/An_alien_landscape_of_chalk-rock%21.jpg",
    "title": "File:An alien landscape of chalk-rock!.jpg",
    "license": "CC BY-SA 4.0",
    "artist": "<a href=\"//commons.wikimedia.org/w/index.php?title=User:AmiraAdel93&amp;action=edit&amp;redlink=1\" class=\"new\" title=\"User:AmiraAdel93 (page does not exist)\">AmiraAdel93</a>",
    "width": 5029,
    "height": 3353,
    "source": "wikimedia_categories",
    "downloaded_at": "2026-03-03T01:05:54"
  },
  {
    "filename": "372f09f4b023299c.jpg",
    "original_url": "https://upload.wikimedia.org/wikipedia/commons/6/6c/Desert_blanc.jpg",
    "title": "File:Desert blanc.jpg",
    "license": "Public domain",
    "artist": "Daniel Fafard",
    "width": 3888,
    "height": 2592,
    "source": "wikimedia_categories",
    "downloaded_at": "2026-03-03T01:05:54"
  },
  {
    "filename": "b2360163c0f3acc1.jpg",
    "original_url": "https://upload.wikimedia.org/wikipedia/commons/7/7c/Egypt_White_Desert_The_Mushroom.jpg",
    "title": "File:Egypt White Desert The Mushroom.jpg",
    "license": "Public domain",
    "artist": "<a href=\"//commons.wikimedia.org/w/index.php?title=User:Nearodney&amp;action=edit&amp;redlink=1\" class=\"new\" title=\"User:Nearodney (page does not exist)\">Nearodney</a>",
    "width": 2848,
    "height": 4272,
    "source": "wikimedia_categories",
    "downloaded_at": "2026-03-03T01:05:54"
  },
  {
    "filename": "2e89764effe36ad8.jpg",
    "original_url": "https://upload.wikimedia.org/wikipedia/commons/e/e8/Flickr_-_neiljs_-_White_desert%2C_Egypt.jpg",
    "title": "File:Flickr - neiljs - White desert, Egypt.jpg",
    "license": "CC BY 2.0",
    "artist": "<a rel=\"nofollow\" class=\"external text\" href=\"https://www.flickr.com/people/59367690@N00\">neiljs</a>",
    "width": 1024,
    "height": 768,
    "source": "wikimedia_categories",
    "downloaded_at": "2026-03-03T01:05:54"
  },
  {
    "filename": "de10bd43bb0cfca7.jpg",
    "original_url": "https://upload.wikimedia.org/wikipedia/commons/a/a3/Desert_fox_%28Vulpes_rueppellii%29.jpg",
    "title": "File:Desert fox (Vulpes rueppellii).jpg",
    "license": "CC BY-SA 3.0",
    "artist": "<a href=\"//commons.wikimedia.org/wiki/User:Theklan\" title=\"User:Theklan\">Theklan</a>",
    "width": 3872,
    "height": 2592,
    "source": "wikimedia_categories",
    "downloaded_at": "2026-03-03T01:05:54"
  },
  {
    "filename": "1b8959ee475c6965.jpg",
    "original_url": "https://upload.wikimedia.org/wikipedia/commons/f/fb/Mushroom_rock_1.jpg",
    "title": "File:Mushroom rock 1.jpg",
    "license": "CC BY-SA 3.0",
    "artist": "<a href=\"//commons.wikimedia.org/w/index.php?title=User:Fathi.hawas&amp;action=edit&amp;redlink=1\" class=\"new\" title=\"User:Fathi.hawas (page does not exist)\">Fathi.hawas</a>",
    "width": 4928,
    "height": 3264,
    "source": "wikimedia_categories",
    "downloaded_at": "2026-03-03T01:05:54"
  },
  {
    "filename": "38623d55dd627dc5.jpg",
    "original_url": "https://upload.wikimedia.org/wikipedia/commons/7/71/Mushroom_rock_2.jpg",
    "title": "File:Mushroom rock 2.jpg",
    "license": "CC BY-SA 3.0",
    "artist": "<a href=\"//commons.wikimedia.org/w/index.php?title=User:Fathi.hawas&amp;action=edit&amp;redlink=1\" class=\"new\" title=\"User:Fathi.hawas (page does not exist)\">Fathi.hawas</a>",
    "width": 4072,
    "height": 2291,
    "source": "wikimedia_categories",
    "downloaded_at": "2026-03-03T01:05:54"
  },
  {
    "filename": "d4ca44365edb164d.jpg",
    "original_url": "https://upload.wikimedia.org/wikipedia/commons/0/02/Mushroom_rock_3.jpg",
    "title": "File:Mushroom rock 3.jpg",
    "license": "CC BY-SA 3.0",
    "artist": "<a href=\"//commons.wikimedia.org/w/index.php?title=User:Fathi.hawas&amp;action=edit&amp;redlink=1\" class=\"new\" title=\"User:Fathi.hawas (page does not exist)\">Fathi.hawas</a>",
    "width": 3264,
    "height": 4928,
    "source": "wikimedia_categories",
    "downloaded_at": "2026-03-03T01:05:54"
  },
  {
    "filename": "2030800050dd8160.jpg",
    "original_url": "https://upload.wikimedia.org/wikipedia/commons/3/34/Oasis_white_desert.jpg",
    "title": "File:Oasis white desert.jpg",
    "license": "CC BY-SA 4.0",
    "artist": "<a href=\"//commons.wikimedia.org/w/index.php?title=User:Ahmed.r.khalil&amp;action=edit&amp;redlink=1\" class=\"new\" title=\"User:Ahmed.r.khalil (page does not exist)\">Ahmed Khalil</a>",
    "width": 4252,
    "height": 2835,
    "source": "wikimedia_categories",
    "downloaded_at": "2026-03-03T01:05:54"
  },
  {
    "filename": "a2723c8bc88e62c6.jpg",
    "original_url": "https://upload.wikimedia.org/wikipedia/commons/d/d6/Desert_fox_%28Vulpes_rueppellii%29_cropped.jpg",
    "title": "File:Desert fox (Vulpes rueppellii) cropped.jpg",
    "license": "CC BY-SA 3.0",
    "artist": "<a href=\"//commons.wikimedia.org/wiki/User:Theklan\" title=\"User:Theklan\">Theklan</a>",
    "width": 830,
    "height": 790,
    "source": "wikimedia_categories",
    "downloaded_at": "2026-03-03T01:05:54"
  },
  {
    "filename": "c7ae551779f81e9e.jpg",
    "original_url": "https://upload.wikimedia.org/wikipedia/commons/5/5e/Vulpes_rueppellii_New_White_Desert%2C_Egypt_%28cropped%29.jpg",
    "title": "File:Vulpes rueppellii New White Desert, Egypt (cropped).jpg",
    "license": "CC BY-SA 2.0",
    "artist": "<a rel=\"nofollow\" class=\"external text\" href=\"https://www.flickr.com/photos/egraf/\">Ernesto Graf</a>",
    "width": 2050,
    "height": 1519,
    "source": "wikimedia_categories",
    "downloaded_at": "2026-03-03T01:05:54"
  },
  {
    "filename": "c966874590141b29.jpg",
    "original_url": "https://upload.wikimedia.org/wikipedia/commons/2/2d/Mushroom_rock_at_white_desert.jpg",
    "title": "File:Mushroom rock at white desert.jpg",
    "license": "CC BY-SA 4.0",
    "artist": "<a href=\"//commons.wikimedia.org/w/index.php?title=User:Asgalal&amp;action=edit&amp;redlink=1\" class=\"new\" title=\"User:Asgalal (page does not exist)\">Asgalal</a>",
    "width": 1920,
    "height": 1363,
    "source": "wikimedia_categories",
    "downloaded_at": "2026-03-03T01:05:54"
  },
  {
    "filename": "a20eeef7f4387cfe.jpg",
    "original_url": "https://upload.wikimedia.org/wikipedia/commons/f/fa/Hill_at_the_white_desert.jpg",
    "title": "File:Hill at the white desert.jpg",
    "license": "CC BY-SA 4.0",
    "artist": "<a href=\"//commons.wikimedia.org/w/index.php?title=User:Asgalal&amp;action=edit&amp;redlink=1\" class=\"new\" title=\"User:Asgalal (page does not exist)\">Asgalal</a>",
    "width": 1920,
    "height": 1280,
    "source": "wikimedia_categories",
    "downloaded_at": "2026-03-03T01:05:54"
  },
  {
    "filename": "88018777c5c236bf.jpg",
    "original_url": "https://upload.wikimedia.org/wikipedia/commons/0/0e/Flickr_-_neiljs_-_White_desert%2C_Egypt_%281%29.jpg",
    "title": "File:Flickr - neiljs - White desert, Egypt (1).jpg",
    "license": "CC BY 2.0",
    "artist": "<a rel=\"nofollow\" class=\"external text\" href=\"https://www.flickr.com/people/59367690@N00\">neiljs</a>",
    "width": 1758,
    "height": 1161,
    "source": "wikimedia_categories",
    "downloaded_at": "2026-03-03T01:05:54"
  },
  {
    "filename": "542321e91969eee7.jpg",
    "original_url": "https://upload.wikimedia.org/wikipedia/commons/5/5f/White_desert_%284014264183%29.jpg",
    "title": "File:White desert (4014264183).jpg",
    "license": "CC BY-SA 2.0",
    "artist": "<a rel=\"nofollow\" class=\"external text\" href=\"https://www.flickr.com/people/43423301@N07\">M M</a> from Switzerland",
    "width": 3872,
    "height": 2592,
    "source": "wikimedia_categories",
    "downloaded_at": "2026-03-03T01:05:54"
  },
  {
    "filename": "cc4cff57f70ed3ad.jpg",
    "original_url": "https://upload.wikimedia.org/wikipedia/commons/3/31/White_desert_%284015027586%29.jpg",
    "title": "File:White desert (4015027586).jpg",
    "license": "CC BY-SA 2.0",
    "artist": "<a rel=\"nofollow\" class=\"external text\" href=\"https://www.flickr.com/people/43423301@N07\">M M</a> from Switzerland",
    "width": 3872,
    "height": 2592,
    "source": "wikimedia_categories",
    "downloaded_at": "2026-03-03T01:05:54"
  },
  {
    "filename": "664df1b4cb7bc96e.jpg",
    "original_url": "https://upload.wikimedia.org/wikipedia/commons/1/1d/White_desert_-_panoramio.jpg",
    "title": "File:White desert - panoramio.jpg",
    "license": "CC BY 3.0",
    "artist": "<a rel=\"nofollow\" class=\"external text\" href=\"https://web.archive.org/web/20161029034325/http://www.panoramio.com/user/7771407?with_photo_id=100915237\">L-BBE</a>",
    "width": 3589,
    "height": 5384,
    "source": "wikimedia_categories",
    "downloaded_at": "2026-03-03T01:05:54"
  },
  {
    "filename": "d7fd4e4e9bb54335.jpg",
    "original_url": "https://upload.wikimedia.org/wikipedia/commons/4/4f/White_Desert_%281%29.jpg",
    "title": "File:White Desert (1).jpg",
    "license": "CC BY-SA 4.0",
    "artist": "<a href=\"//commons.wikimedia.org/wiki/User:Myousry6666\" title=\"User:Myousry6666\">Myousry6666</a>",
    "width": 4096,
    "height": 2730,
    "source": "wikimedia_categories",
    "downloaded_at": "2026-03-03T01:05:54"
  },
  {
    "filename": "482018bcd3c741dc.jpg",
    "original_url": "https://upload.wikimedia.org/wikipedia/commons/4/45/White_Desert_%282%29.jpg",
    "title": "File:White Desert (2).jpg",
    "license": "CC BY-SA 4.0",
    "artist": "<a href=\"//commons.wikimedia.org/wiki/User:Myousry6666\" title=\"User:Myousry6666\">Myousry6666</a>",
    "width": 5315,
    "height": 3543,
    "source": "wikimedia_categories",
    "downloaded_at": "2026-03-03T01:05:54"
  },
  {
    "filename": "8740932cd0e3302f.jpg",
    "original_url": "https://upload.wikimedia.org/wikipedia/commons/6/65/Vulpes_rueppellii_New_White_Desert%2C_Egypt.jpg",
    "title": "File:Vulpes rueppellii New White Desert, Egypt.jpg",
    "license": "CC BY-SA 2.0",
    "artist": "<a rel=\"nofollow\" class=\"external text\" href=\"https://www.flickr.com/photos/egraf/\">Ernesto Graf</a>",
    "width": 3872,
    "height": 2592,
    "source": "wikimedia_categories",
    "downloaded_at": "2026-03-03T01:05:54"
  },
  {
    "filename": "68e5e1c4098c65be.jpg",
    "original_url": "https://upload.wikimedia.org/wikipedia/commons/0/0b/White_desert_-_IMG_2264.jpg",
    "title": "File:White desert - IMG 2264.jpg",
    "license": "CC BY-SA 4.0",
    "artist": "<a href=\"//commons.wikimedia.org/w/index.php?title=User:Dalia_Farid_75&amp;action=edit&amp;redlink=1\" class=\"new\" title=\"User:Dalia Farid 75 (page does not exist)\">Dalia Farid </a>",
    "width": 5358,
    "height": 2979,
    "source": "wikimedia_categories",
    "downloaded_at": "2026-03-03T01:05:54"
  },
  {
    "filename": "7e057a2f70c83db2.jpg",
    "original_url": "https://upload.wikimedia.org/wikipedia/commons/b/b2/White_desert_00.jpg",
    "title": "File:White desert 00.jpg",
    "license": "CC BY-SA 4.0",
    "artist": "<a href=\"//commons.wikimedia.org/wiki/User:Ahmedsalahemam\" title=\"User:Ahmedsalahemam\">Ahmedsalahemam</a>",
    "width": 4928,
    "height": 3264,
    "source": "wikimedia_categories",
    "downloaded_at": "2026-03-03T01:05:54"
  },
  {
    "filename": "1f7260e31870107f.jpg",
    "original_url": "https://upload.wikimedia.org/wikipedia/commons/4/41/White_desert_2.jpg",
    "title": "File:White desert 2.jpg",
    "license": "CC BY-SA 3.0",
    "artist": "<a href=\"//commons.wikimedia.org/w/index.php?title=User:Fathi.hawas&amp;action=edit&amp;redlink=1\" class=\"new\" title=\"User:Fathi.hawas (page does not exist)\">Fathi.hawas</a>",
    "width": 4887,
    "height": 2749,
    "source": "wikimedia_categories",
    "downloaded_at": "2026-03-03T01:05:54"
  },
  {
    "filename": "68391e6caf52259d.jpg",
    "original_url": "https://upload.wikimedia.org/wikipedia/commons/8/8f/White_Desert_star_trail.jpg",
    "title": "File:White Desert star trail.jpg",
    "license": "CC BY-SA 4.0",
    "artist": "<a href=\"//commons.wikimedia.org/w/index.php?title=User:Ahmed.r.khalil&amp;action=edit&amp;redlink=1\" class=\"new\" title=\"User:Ahmed.r.khalil (page does not exist)\">Ahmed Khalil</a>",
    "width": 4288,
    "height": 2848,
    "source": "wikimedia_categories",
    "downloaded_at": "2026-03-03T01:05:54"
  },
  {
    "filename": "299cb54ee2c03802.jpg",
    "original_url": "https://upload.wikimedia.org/wikipedia/commons/6/6e/White_Desert_2.jpg",
    "title": "File:White Desert 2.jpg",
    "license": "CC BY-SA 4.0",
    "artist": "<a href=\"//commons.wikimedia.org/wiki/User:Myousry6666\" title=\"User:Myousry6666\">Mohamed Ahmed Yousry</a>",
    "width": 5315,
    "height": 3543,
    "source": "wikimedia_categories",
    "downloaded_at": "2026-03-03T01:05:54"
  },
  {
    "filename": "d2f9c7240a078d0e.jpg",
    "original_url": "https://upload.wikimedia.org/wikipedia/commons/3/3e/White_Desert_3.jpg",
    "title": "File:White Desert 3.jpg",
    "license": "CC BY-SA 4.0",
    "artist": "<a href=\"//commons.wikimedia.org/wiki/User:Myousry6666\" title=\"User:Myousry6666\">Mohamed Ahmed Yousry</a>",
    "width": 5315,
    "height": 3543,
    "source": "wikimedia_categories",
    "downloaded_at": "2026-03-03T01:05:54"
  },
  {
    "filename": "fa66580f8aa271d8.jpg",
    "original_url": "https://upload.wikimedia.org/wikipedia/commons/3/36/White_Desert_1.jpg",
    "title": "File:White Desert 1.jpg",
    "license": "CC BY-SA 4.0",
    "artist": "<a href=\"//commons.wikimedia.org/wiki/User:Myousry6666\" title=\"User:Myousry6666\">Mohamed Ahmed Yousry</a>",
    "width": 5315,
    "height": 3543,
    "source": "wikimedia_categories",
    "downloaded_at": "2026-03-03T01:05:54"
  },
  {
    "filename": "a699cb5e7f3cc3f7.jpg",
    "original_url": "https://upload.wikimedia.org/wikipedia/commons/b/b9/White_Desert_5.jpg",
    "title": "File:White Desert 5.jpg",
    "license": "CC BY-SA 4.0",
    "artist": "<a href=\"//commons.wikimedia.org/wiki/User:Myousry6666\" title=\"User:Myousry6666\">Mohamed Ahmed Yousry</a>",
    "width": 3543,
    "height": 5315,
    "source": "wikimedia_categories",
    "downloaded_at": "2026-03-03T01:05:54"
  },
  {
    "filename": "e78bd9c6a4b68cd5.jpg",
    "original_url": "https://upload.wikimedia.org/wikipedia/commons/7/7c/White_Desert_4.jpg",
    "title": "File:White Desert 4.jpg",
    "license": "CC BY-SA 4.0",
    "artist": "<a href=\"//commons.wikimedia.org/wiki/User:Myousry6666\" title=\"User:Myousry6666\">Mohamed Ahmed Yousry</a>",
    "width": 4000,
    "height": 6000,
    "source": "wikimedia_categories",
    "downloaded_at": "2026-03-03T01:05:54"
  },
  {
    "filename": "6aff6a3e0969fd3f.jpg",
    "original_url": "https://upload.wikimedia.org/wikipedia/commons/c/cc/White_Desert_6.jpg",
    "title": "File:White Desert 6.jpg",
    "license": "CC BY-SA 4.0",
    "artist": "<a href=\"//commons.wikimedia.org/wiki/User:Myousry6666\" title=\"User:Myousry6666\">Mohamed Ahmed Yousry</a>",
    "width": 5315,
    "height": 3543,
    "source": "wikimedia_categories",
    "downloaded_at": "2026-03-03T01:05:54"
  },
  {
    "filename": "ccf0f361642fdaf8.jpg",
    "original_url": "https://upload.wikimedia.org/wikipedia/commons/b/b9/White_desert_in_night.jpg",
    "title": "File:White desert in night.jpg",
    "license": "CC BY-SA 4.0",
    "artist": "<a href=\"//commons.wikimedia.org/w/index.php?title=User:Ahmed_Yousry_Mahfouz&amp;action=edit&amp;redlink=1\" class=\"new\" title=\"User:Ahmed Yousry Mahfouz (page does not exist)\">Ahmed Yousry Mahfouz</a>",
    "width": 4724,
    "height": 3149,
    "source": "wikimedia_categories",
    "downloaded_at": "2026-03-03T01:05:54"
  },
  {
    "filename": "251ce2467c93b18c.jpg",
    "original_url": "https://upload.wikimedia.org/wikipedia/commons/b/bf/White_desert_sunset_time.jpg",
    "title": "File:White desert sunset time.jpg",
    "license": "CC BY-SA 4.0",
    "artist": "<a href=\"//commons.wikimedia.org/w/index.php?title=User:Ahmed_Yousry_Mahfouz&amp;action=edit&amp;redlink=1\" class=\"new\" title=\"User:Ahmed Yousry Mahfouz (page does not exist)\">Ahmed Yousry Mahfouz</a>",
    "width": 4252,
    "height": 2835,
    "source": "wikimedia_categories",
    "downloaded_at": "2026-03-03T01:05:54"
  },
  {
    "filename": "70bbae3d2dc305ed.jpg",
    "original_url": "https://upload.wikimedia.org/wikipedia/commons/1/1b/White_Desert_2%2C_Egypt.jpg",
    "title": "File:White Desert 2, Egypt.jpg",
    "license": "CC BY 4.0",
    "artist": "<a href=\"//commons.wikimedia.org/wiki/User:Argenberg\" title=\"User:Argenberg\">Vyacheslav Argenberg</a>",
    "width": 3072,
    "height": 2048,
    "source": "wikimedia_categories",
    "downloaded_at": "2026-03-03T01:05:54"
  },
  {
    "filename": "8e23304d8bae7982.jpg",
    "original_url": "https://upload.wikimedia.org/wikipedia/commons/8/80/White_Desert%2C_Al-Farafra-Al-Bahariya_road_through_the_desert%2C_Egypt.jpg",
    "title": "File:White Desert, Al-Farafra-Al-Bahariya road through the desert, Egypt.jpg",
    "license": "CC BY 4.0",
    "artist": "<a href=\"//commons.wikimedia.org/wiki/User:Argenberg\" title=\"User:Argenberg\">Vyacheslav Argenberg</a>",
    "width": 3072,
    "height": 2048,
    "source": "wikimedia_categories",
    "downloaded_at": "2026-03-03T01:05:54"
  },
  {
    "filename": "056da2f7c56e58e9.jpg",
    "original_url": "https://upload.wikimedia.org/wikipedia/commons/5/5b/White_Desert%2C_Al-Farafra-Al-Bahariya_road%2C_Egypt.jpg",
    "title": "File:White Desert, Al-Farafra-Al-Bahariya road, Egypt.jpg",
    "license": "CC BY 4.0",
    "artist": "<a href=\"//commons.wikimedia.org/wiki/User:Argenberg\" title=\"User:Argenberg\">Vyacheslav Argenberg</a>",
    "width": 3072,
    "height": 2048,
    "source": "wikimedia_categories",
    "downloaded_at": "2026-03-03T01:05:54"
  },
  {
    "filename": "c464c8c939baf613.jpg",
    "original_url": "https://upload.wikimedia.org/wikipedia/commons/f/f5/White_desert.jpg",
    "title": "File:White desert.jpg",
    "license": "CC0",
    "artist": "<a href=\"//commons.wikimedia.org/w/index.php?title=User:Ysjyd&amp;action=edit&amp;redlink=1\" class=\"new\" title=\"User:Ysjyd (page does not exist)\">Ysjyd</a>",
    "width": 3888,
    "height": 2592,
    "source": "wikimedia_categories",
    "downloaded_at": "2026-03-03T01:05:54"
  },
  {
    "filename": "b8f042f311fbb695.jpg",
    "original_url": "https://upload.wikimedia.org/wikipedia/commons/2/2a/White_Desert1.jpg",
    "title": "File:White Desert1.jpg",
    "license": "CC BY-SA 4.0",
    "artist": "<a href=\"//commons.wikimedia.org/w/index.php?title=User:Ahmed.r.khalil&amp;action=edit&amp;redlink=1\" class=\"new\" title=\"User:Ahmed.r.khalil (page does not exist)\">Ahmed Khalil</a>",
    "width": 3729,
    "height": 2476,
    "source": "wikimedia_categories",
    "downloaded_at": "2026-03-03T01:05:54"
  },
  {
    "filename": "a66904d1ed6d946b.jpg",
    "original_url": "https://upload.wikimedia.org/wikipedia/commons/e/eb/White_desert10.jpg",
    "title": "File:White desert10.jpg",
    "license": "CC BY-SA 4.0",
    "artist": "<a href=\"//commons.wikimedia.org/w/index.php?title=User:Ahmed.r.khalil&amp;action=edit&amp;redlink=1\" class=\"new\" title=\"User:Ahmed.r.khalil (page does not exist)\">Ahmed Khalil</a>",
    "width": 3008,
    "height": 2000,
    "source": "wikimedia_categories",
    "downloaded_at": "2026-03-03T01:05:54"
  },
  {
    "filename": "a6f2970cf9b2e9d5.jpg",
    "original_url": "https://upload.wikimedia.org/wikipedia/commons/0/06/White_desert11.jpg",
    "title": "File:White desert11.jpg",
    "license": "CC BY-SA 4.0",
    "artist": "<a href=\"//commons.wikimedia.org/w/index.php?title=User:Ahmed.r.khalil&amp;action=edit&amp;redlink=1\" class=\"new\" title=\"User:Ahmed.r.khalil (page does not exist)\">Ahmed Khalil</a>",
    "width": 1901,
    "height": 2859,
    "source": "wikimedia_categories",
    "downloaded_at": "2026-03-03T01:05:54"
  },
  {
    "filename": "15da55ba85916aa3.jpg",
    "original_url": "https://upload.wikimedia.org/wikipedia/commons/f/f8/White_Desert13.jpg",
    "title": "File:White Desert13.jpg",
    "license": "CC BY-SA 4.0",
    "artist": "<a href=\"//commons.wikimedia.org/w/index.php?title=User:Ahmed.r.khalil&amp;action=edit&amp;redlink=1\" class=\"new\" title=\"User:Ahmed.r.khalil (page does not exist)\">Ahmed Khalil</a>",
    "width": 3008,
    "height": 1590,
    "source": "wikimedia_categories",
    "downloaded_at": "2026-03-03T01:05:54"
  },
  {
    "filename": "d6e31ec26dcb005e.jpg",
    "original_url": "https://upload.wikimedia.org/wikipedia/commons/b/b4/White_Desert%2C_Sky%2C_Egypt.jpg",
    "title": "File:White Desert, Sky, Egypt.jpg",
    "license": "CC BY 4.0",
    "artist": "<a href=\"//commons.wikimedia.org/wiki/User:Argenberg\" title=\"User:Argenberg\">Vyacheslav Argenberg</a>",
    "width": 3072,
    "height": 2048,
    "source": "wikimedia_categories",
    "downloaded_at": "2026-03-03T01:05:54"
  },
  {
    "filename": "dbb840b6983eb4dc.jpg",
    "original_url": "https://upload.wikimedia.org/wikipedia/commons/0/0b/White_Desert%2C_Camels%2C_Egypt.jpg",
    "title": "File:White Desert, Camels, Egypt.jpg",
    "license": "CC BY 4.0",
    "artist": "<a href=\"//commons.wikimedia.org/wiki/User:Argenberg\" title=\"User:Argenberg\">Vyacheslav Argenberg</a>",
    "width": 3072,
    "height": 2048,
    "source": "wikimedia_categories",
    "downloaded_at": "2026-03-03T01:05:54"
  },
  {
    "filename": "7ab56232ab968a94.jpg",
    "original_url": "https://upload.wikimedia.org/wikipedia/commons/2/26/White_Desert%2C_Stark_desert_landscape%2C_Rock_formations%2C_Egypt.jpg",
    "title": "File:White Desert, Stark desert landscape, Rock formations, Egypt.jpg",
    "license": "CC BY 4.0",
    "artist": "<a href=\"//commons.wikimedia.org/wiki/User:Argenberg\" title=\"User:Argenberg\">Vyacheslav Argenberg</a>",
    "width": 3072,
    "height": 2048,
    "source": "wikimedia_categories",
    "downloaded_at": "2026-03-03T01:05:54"
  },
  {
    "filename": "361c07ab13a30e71.jpg",
    "original_url": "https://upload.wikimedia.org/wikipedia/commons/0/0e/White_Desert%2C_Rock_formations%2C_Egypt.jpg",
    "title": "File:White Desert, Rock formations, Egypt.jpg",
    "license": "CC BY 4.0",
    "artist": "<a href=\"//commons.wikimedia.org/wiki/User:Argenberg\" title=\"User:Argenberg\">Vyacheslav Argenberg</a>",
    "width": 3072,
    "height": 2048,
    "source": "wikimedia_categories",
    "downloaded_at": "2026-03-03T01:05:54"
  },
  {
    "filename": "b5bffe89b92439b7.jpg",
    "original_url": "https://upload.wikimedia.org/wikipedia/commons/0/02/White_Desert%2C_Farafra_depression%2C_Egypt.jpg",
    "title": "File:White Desert, Farafra depression, Egypt.jpg",
    "license": "CC BY 4.0",
    "artist": "<a href=\"//commons.wikimedia.org/wiki/User:Argenberg\" title=\"User:Argenberg\">Vyacheslav Argenberg</a>",
    "width": 3072,
    "height": 2048,
    "source": "wikimedia_categories",
    "downloaded_at": "2026-03-03T01:05:54"
  },
  {
    "filename": "f31017fa1ba44b1e.jpg",
    "original_url": "https://upload.wikimedia.org/wikipedia/commons/f/f9/White_Desert%2C_Desert_landscape%2C_Egypt.jpg",
    "title": "File:White Desert, Desert landscape, Egypt.jpg",
    "license": "CC BY 4.0",
    "artist": "<a href=\"//commons.wikimedia.org/wiki/User:Argenberg\" title=\"User:Argenberg\">Vyacheslav Argenberg</a>",
    "width": 3072,
    "height": 2048,
    "source": "wikimedia_categories",
    "downloaded_at": "2026-03-03T01:05:54"
  },
  {
    "filename": "78871199808b4fcd.jpg",
    "original_url": "https://upload.wikimedia.org/wikipedia/commons/c/ce/White_Desert%2C_Karst_rock_formations%2C_Egypt.jpg",
    "title": "File:White Desert, Karst rock formations, Egypt.jpg",
    "license": "CC BY 4.0",
    "artist": "<a href=\"//commons.wikimedia.org/wiki/User:Argenberg\" title=\"User:Argenberg\">Vyacheslav Argenberg</a>",
    "width": 3072,
    "height": 2048,
    "source": "wikimedia_categories",
    "downloaded_at": "2026-03-03T01:05:54"
  },
  {
    "filename": "a98facde15d21b47.jpg",
    "original_url": "https://upload.wikimedia.org/wikipedia/commons/4/44/White_Desert%2C_Karst_rock_formations_2%2C_Egypt.jpg",
    "title": "File:White Desert, Karst rock formations 2, Egypt.jpg",
    "license": "CC BY 4.0",
    "artist": "<a href=\"//commons.wikimedia.org/wiki/User:Argenberg\" title=\"User:Argenberg\">Vyacheslav Argenberg</a>",
    "width": 3072,
    "height": 2048,
    "source": "wikimedia_categories",
    "downloaded_at": "2026-03-03T01:05:54"
  },
  {
    "filename": "fc2cc80bc2c02fa7.jpg",
    "original_url": "https://upload.wikimedia.org/wikipedia/commons/8/8d/White_Desert%2C_Egypt.jpg",
    "title": "File:White Desert, Egypt.jpg",
    "license": "CC BY 4.0",
    "artist": "<a href=\"//commons.wikimedia.org/wiki/User:Argenberg\" title=\"User:Argenberg\">Vyacheslav Argenberg</a>",
    "width": 3072,
    "height": 2048,
    "source": "wikimedia_categories",
    "downloaded_at": "2026-03-03T01:05:54"
  },
  {
    "filename": "74a0dad4bd3dc41a.jpg",
    "original_url": "https://upload.wikimedia.org/wikipedia/commons/1/14/White_Desert%2C_Rock_formation%2C_Egypt.jpg",
    "title": "File:White Desert, Rock formation, Egypt.jpg",
    "license": "CC BY 4.0",
    "artist": "<a href=\"//commons.wikimedia.org/wiki/User:Argenberg\" title=\"User:Argenberg\">Vyacheslav Argenberg</a>",
    "width": 3072,
    "height": 2048,
    "source": "wikimedia_categories",
    "downloaded_at": "2026-03-03T01:05:54"
  },
  {
    "filename": "699048f0d3b99170.jpg",
    "original_url": "https://upload.wikimedia.org/wikipedia/commons/3/32/White_Desert%2C_Palm_in_desert_landscape%2C_Egypt.jpg",
    "title": "File:White Desert, Palm in desert landscape, Egypt.jpg",
    "license": "CC BY 4.0",
    "artist": "<a href=\"//commons.wikimedia.org/wiki/User:Argenberg\" title=\"User:Argenberg\">Vyacheslav Argenberg</a>",
    "width": 3072,
    "height": 2048,
    "source": "wikimedia_categories",
    "downloaded_at": "2026-03-03T01:05:54"
  },
  {
    "filename": "73a7a8722dccb6c9.jpg",
    "original_url": "https://upload.wikimedia.org/wikipedia/commons/f/fd/White_Desert%2C_Rock_formations_in_desert_landscape_2%2C_Egypt.jpg",
    "title": "File:White Desert, Rock formations in desert landscape 2, Egypt.jpg",
    "license": "CC BY 4.0",
    "artist": "<a href=\"//commons.wikimedia.org/wiki/User:Argenberg\" title=\"User:Argenberg\">Vyacheslav Argenberg</a>",
    "width": 3072,
    "height": 2048,
    "source": "wikimedia_categories",
    "downloaded_at": "2026-03-03T01:05:54"
  },
  {
    "filename": "1352a0088ca85fe1.jpg",
    "original_url": "https://upload.wikimedia.org/wikipedia/commons/c/cb/White_Desert%2C_Alien_landscape%2C_Egypt.jpg",
    "title": "File:White Desert, Alien landscape, Egypt.jpg",
    "license": "CC BY 4.0",
    "artist": "<a href=\"//commons.wikimedia.org/wiki/User:Argenberg\" title=\"User:Argenberg\">Vyacheslav Argenberg</a>",
    "width": 3072,
    "height": 2048,
    "source": "wikimedia_categories",
    "downloaded_at": "2026-03-03T01:05:54"
  },
  {
    "filename": "4fd6a4f96f30d072.jpg",
    "original_url": "https://upload.wikimedia.org/wikipedia/commons/1/16/White_Desert%2C_Rock_formations_in_desert_landscape%2C_Egypt.jpg",
    "title": "File:White Desert, Rock formations in desert landscape, Egypt.jpg",
    "license": "CC BY 4.0",
    "artist": "<a href=\"//commons.wikimedia.org/wiki/User:Argenberg\" title=\"User:Argenberg\">Vyacheslav Argenberg</a>",
    "width": 3072,
    "height": 2048,
    "source": "wikimedia_categories",
    "downloaded_at": "2026-03-03T01:05:54"
  },
  {
    "filename": "bf8ee18747bcb2f7.jpg",
    "original_url": "https://upload.wikimedia.org/wikipedia/commons/d/db/White_Desert%2C_Road_through_the_desert%2C_Egypt.jpg",
    "title": "File:White Desert, Road through the desert, Egypt.jpg",
    "license": "CC BY 4.0",
    "artist": "<a href=\"//commons.wikimedia.org/wiki/User:Argenberg\" title=\"User:Argenberg\">Vyacheslav Argenberg</a>",
    "width": 3072,
    "height": 2048,
    "source": "wikimedia_categories",
    "downloaded_at": "2026-03-03T01:05:54"
  },
  {
    "filename": "63fed82952345dd2.jpg",
    "original_url": "https://upload.wikimedia.org/wikipedia/commons/f/fb/White-desert-egypt.jpg",
    "title": "File:White-desert-egypt.jpg",
    "license": "CC BY-SA 2.5",
    "artist": "No machine-readable author provided. <a href=\"//commons.wikimedia.org/wiki/User:Nomo\" title=\"User:Nomo\">Nomo</a> assumed (based on copyright claims).",
    "width": 1200,
    "height": 412,
    "source": "wikimedia_categories",
    "downloaded_at": "2026-03-03T01:05:54"
  },
  {
    "filename": "f4325c0a4b25408b.jpg",
    "original_url": "https://upload.wikimedia.org/wikipedia/commons/e/e8/WhiteDesertEgypt%40FarafraOasis2007jan6-01_byDanielCsorfoly.JPG",
    "title": "File:WhiteDesertEgypt@FarafraOasis2007jan6-01 byDanielCsorfoly.JPG",
    "license": "Public domain",
    "artist": "Daniel Csörföly",
    "width": 1200,
    "height": 900,
    "source": "wikimedia_categories",
    "downloaded_at": "2026-03-03T01:05:54"
  },
  {
    "filename": "00d1d3093ebdb9fd.jpg",
    "original_url": "https://upload.wikimedia.org/wikipedia/commons/4/42/WhiteDesertEgypt%40FarafraOasis2007jan6-02_byDanielCsorfoly.JPG",
    "title": "File:WhiteDesertEgypt@FarafraOasis2007jan6-02 byDanielCsorfoly.JPG",
    "license": "Public domain",
    "artist": "Daniel Csörföly",
    "width": 1200,
    "height": 900,
    "source": "wikimedia_categories",
    "downloaded_at": "2026-03-03T01:05:54"
  },
  {
    "filename": "36ee3a6e5a9e89b9.jpg",
    "original_url": "https://upload.wikimedia.org/wikipedia/commons/5/53/WhiteDesertEgypt%40FarafraOasis2007jan6-04_byDanielCsorfoly.JPG",
    "title": "File:WhiteDesertEgypt@FarafraOasis2007jan6-04 byDanielCsorfoly.JPG",
    "license": "Public domain",
    "artist": "Daniel Csörföly",
    "width": 1200,
    "height": 900,
    "source": "wikimedia_categories",
    "downloaded_at": "2026-03-03T01:05:54"
  },
  {
    "filename": "e1d82afa80bbd48b.jpg",
    "original_url": "https://upload.wikimedia.org/wikipedia/commons/3/34/WhiteDesertEgypt%40FarafraOasis2007jan6-05_byDanielCsorfoly.JPG",
    "title": "File:WhiteDesertEgypt@FarafraOasis2007jan6-05 byDanielCsorfoly.JPG",
    "license": "Public domain",
    "artist": "Daniel Csörföly",
    "width": 1200,
    "height": 900,
    "source": "wikimedia_categories",
    "downloaded_at": "2026-03-03T01:05:54"
  },
  {
    "filename": "1d4729b90363bc67.jpg",
    "original_url": "https://upload.wikimedia.org/wikipedia/commons/3/32/WhiteDesertEgypt%40FarafraOasis2007jan6-06_byDanielCsorfoly.JPG",
    "title": "File:WhiteDesertEgypt@FarafraOasis2007jan6-06 byDanielCsorfoly.JPG",
    "license": "Public domain",
    "artist": "Daniel Csörföly",
    "width": 1200,
    "height": 900,
    "source": "wikimedia_categories",
    "downloaded_at": "2026-03-03T01:05:54"
  },
  {
    "filename": "603ef1eec5b0faf0.jpg",
    "original_url": "https://upload.wikimedia.org/wikipedia/commons/5/54/WhiteDesertEgypt%40FarafraOasis2007jan6-07_byDanielCsorfoly.JPG",
    "title": "File:WhiteDesertEgypt@FarafraOasis2007jan6-07 byDanielCsorfoly.JPG",
    "license": "Public domain",
    "artist": "Daniel Csörföly",
    "width": 1200,
    "height": 900,
    "source": "wikimedia_categories",
    "downloaded_at": "2026-03-03T01:05:54"
  },
  {
    "filename": "2d892d159968b886.jpg",
    "original_url": "https://upload.wikimedia.org/wikipedia/commons/7/78/WhiteDesertAcacia.jpg",
    "title": "File:WhiteDesertAcacia.jpg",
    "license": "CC BY-SA 3.0",
    "artist": "<a href=\"//commons.wikimedia.org/wiki/User:RolandUnger\" title=\"User:RolandUnger\">Roland Unger</a>",
    "width": 800,
    "height": 533,
    "source": "wikimedia_categories",
    "downloaded_at": "2026-03-03T01:05:54"
  },
  {
    "filename": "775e2c7eaafe700f.jpg",
    "original_url": "https://upload.wikimedia.org/wikipedia/commons/2/2b/WhiteDesertCamel.jpg",
    "title": "File:WhiteDesertCamel.jpg",
    "license": "CC BY-SA 3.0",
    "artist": "<a href=\"//commons.wikimedia.org/wiki/User:RolandUnger\" title=\"User:RolandUnger\">Roland Unger</a>",
    "width": 800,
    "height": 533,
    "source": "wikimedia_categories",
    "downloaded_at": "2026-03-03T01:05:54"
  },
  {
    "filename": "edcf8f8e87fc5a6e.jpg",
    "original_url": "https://upload.wikimedia.org/wikipedia/commons/8/87/WhiteDesertDog.jpg",
    "title": "File:WhiteDesertDog.jpg",
    "license": "CC BY-SA 3.0",
    "artist": "<a href=\"//commons.wikimedia.org/wiki/User:RolandUnger\" title=\"User:RolandUnger\">Roland Unger</a>",
    "width": 530,
    "height": 800,
    "source": "wikimedia_categories",
    "downloaded_at": "2026-03-03T01:05:54"
  }
]
